{
    "AX": {
        "error": 0.0,
        "error_type": "SEM",
        "filter_outliers_dict": {
            "filter_outliers": false,
            "iterations": 0,
            "std_devs": 0
        },
        "fit": "Average",
        "fn": 6,
        "include_baseline_error": false,
        "n": 6,
        "reviewed": true,
        "value": 0.0
    },
    "H1": {
        "error": 2.431013406761758e-07,
        "error_type": "SEM",
        "filter_outliers_dict": {
            "filter_outliers": false,
            "iterations": 0,
            "std_devs": 0
        },
        "fit": "Average",
        "fn": 6,
        "include_baseline_error": false,
        "n": 6,
        "reviewed": true,
        "value": -1.0656154122064738e-06
    },
    "H2": {
        "error": 9.611000520757088e-07,
        "error_type": "SEM",
        "filter_outliers_dict": {
            "filter_outliers": false,
            "iterations": 0,
            "std_devs": 0
        },
        "fit": "Average",
        "fn": 6,
        "include_baseline_error": false,
        "n": 6,
        "reviewed": true,
        "value": -2.1728564500259986e-06
    },
    "L1": {
        "error": 2.9633133795621315e-07,
        "error_type": "SEM",
        "filter_outliers_dict": {
            "filter_outliers": false,
            "iterations": 0,
            "std_devs": 0
        },
        "fit": "Average",
        "fn": 12,
        "include_baseline_error": false,
        "n": 12,
        "reviewed": true,
        "value": -4.04498662713119e-07
    },
    "L2": {
        "error": 0.030731815719647188,
        "error_type": "SEM",
        "filter_outliers_dict": {
            "filter_outliers": false,
            "iterations": 0,
            "std_devs": 0
        },
        "fit": "Average",
        "fn": 6,
        "include_baseline_error": false,
        "n": 6,
        "reviewed": true,
        "value": 0.2833333412806193
    }
}