{
    "Ar36": {
        "error": 21.976129256535422,
        "error_type": "SEM",
        "filter_outliers_dict": {
            "filter_outliers": false,
            "iterations": 0,
            "std_devs": 0
        },
        "fit": "Linear",
        "fn": 25,
        "include_baseline_error": false,
        "n": 25,
        "reviewed": true,
        "value": 9545.722152644365
    },
    "Ar36L1": {
        "error": 5.331438411793665e-07,
        "error_type": "SEM",
        "filter_outliers_dict": {
            "filter_outliers": false,
            "iterations": 0,
            "std_devs": 0
        },
        "fit": "Linear",
        "fn": 25,
        "include_baseline_error": false,
        "n": 25,
        "reviewed": true,
        "value": 0.0002138573250877021
    },
    "Ar37": {
        "error": 3.4315412916896925e-07,
        "error_type": "SEM",
        "filter_outliers_dict": {
            "filter_outliers": false,
            "iterations": 0,
            "std_devs": 0
        },
        "fit": "Linear",
        "fn": 25,
        "include_baseline_error": false,
        "n": 25,
        "reviewed": true,
        "value": 7.711148094956992e-05
    },
    "Ar38": {
        "error": 5.104225194669014e-07,
        "error_type": "SEM",
        "filter_outliers_dict": {
            "filter_outliers": false,
            "iterations": 0,
            "std_devs": 0
        },
        "fit": "Linear",
        "fn": 25,
        "include_baseline_error": false,
        "n": 25,
        "reviewed": true,
        "value": 4.6510112188212076e-05
    },
    "Ar39": {
        "error": 5.018802531804459e-07,
        "error_type": "SEM",
        "filter_outliers_dict": {
            "filter_outliers": false,
            "iterations": 0,
            "std_devs": 0
        },
        "fit": "Linear",
        "fn": 25,
        "include_baseline_error": false,
        "n": 25,
        "reviewed": true,
        "value": 0.00023868415750846278
    },
    "Ar40": {
        "error": 1.8990214887048408e-05,
        "error_type": "SEM",
        "filter_outliers_dict": {
            "filter_outliers": false,
            "iterations": 0,
            "std_devs": 0
        },
        "fit": "Linear",
        "fn": 25,
        "include_baseline_error": false,
        "n": 25,
        "reviewed": true,
        "value": 0.06280027386657687
    }
}