{
    "Ar36": {
        "error": 52.114141977766685,
        "error_type": "SEM",
        "filter_outliers_dict": {
            "filter_outliers": false,
            "iterations": 0,
            "std_devs": 0
        },
        "fit": "Linear",
        "fn": 25,
        "include_baseline_error": false,
        "n": 25,
        "reviewed": true,
        "value": 13561.979642157672
    },
    "Ar36L1": {
        "error": 5.234637969093087e-07,
        "error_type": "SEM",
        "filter_outliers_dict": {
            "filter_outliers": false,
            "iterations": 0,
            "std_devs": 0
        },
        "fit": "Linear",
        "fn": 25,
        "include_baseline_error": false,
        "n": 25,
        "reviewed": true,
        "value": 0.0003119319347375633
    },
    "Ar37": {
        "error": 3.2059058767686567e-07,
        "error_type": "SEM",
        "filter_outliers_dict": {
            "filter_outliers": false,
            "iterations": 0,
            "std_devs": 0
        },
        "fit": "Linear",
        "fn": 25,
        "include_baseline_error": false,
        "n": 25,
        "reviewed": true,
        "value": 8.187111393862605e-05
    },
    "Ar38": {
        "error": 5.751634765893187e-07,
        "error_type": "SEM",
        "filter_outliers_dict": {
            "filter_outliers": false,
            "iterations": 0,
            "std_devs": 0
        },
        "fit": "Linear",
        "fn": 25,
        "include_baseline_error": false,
        "n": 25,
        "reviewed": true,
        "value": 8.202744680565108e-05
    },
    "Ar39": {
        "error": 7.417876689500759e-07,
        "error_type": "SEM",
        "filter_outliers_dict": {
            "filter_outliers": false,
            "iterations": 0,
            "std_devs": 0
        },
        "fit": "Linear",
        "fn": 25,
        "include_baseline_error": false,
        "n": 25,
        "reviewed": true,
        "value": 0.001119537664943081
    },
    "Ar40": {
        "error": 3.595735324364038e-05,
        "error_type": "SEM",
        "filter_outliers_dict": {
            "filter_outliers": false,
            "iterations": 0,
            "std_devs": 0
        },
        "fit": "Linear",
        "fn": 25,
        "include_baseline_error": false,
        "n": 25,
        "reviewed": true,
        "value": 0.0910730079208045
    }
}