{
    "Ar36": {
        "error": 119.58457773675786,
        "error_type": "SEM",
        "filter_outliers_dict": {
            "filter_outliers": false,
            "iterations": 0,
            "std_devs": 0
        },
        "fit": "Linear",
        "fn": 25,
        "include_baseline_error": false,
        "n": 25,
        "reviewed": true,
        "value": 33819.12241873148
    },
    "Ar36L1": {
        "error": 7.70603293865678e-07,
        "error_type": "SEM",
        "filter_outliers_dict": {
            "filter_outliers": false,
            "iterations": 0,
            "std_devs": 0
        },
        "fit": "Linear",
        "fn": 25,
        "include_baseline_error": false,
        "n": 25,
        "reviewed": true,
        "value": 0.000761404800458875
    },
    "Ar37": {
        "error": 4.1036398016846333e-07,
        "error_type": "SEM",
        "filter_outliers_dict": {
            "filter_outliers": false,
            "iterations": 0,
            "std_devs": 0
        },
        "fit": "Linear",
        "fn": 25,
        "include_baseline_error": false,
        "n": 25,
        "reviewed": true,
        "value": 6.717528860535597e-05
    },
    "Ar38": {
        "error": 4.538242579709476e-07,
        "error_type": "SEM",
        "filter_outliers_dict": {
            "filter_outliers": false,
            "iterations": 0,
            "std_devs": 0
        },
        "fit": "Linear",
        "fn": 25,
        "include_baseline_error": false,
        "n": 25,
        "reviewed": true,
        "value": 0.00015589073112275858
    },
    "Ar39": {
        "error": 4.607122874727116e-07,
        "error_type": "SEM",
        "filter_outliers_dict": {
            "filter_outliers": false,
            "iterations": 0,
            "std_devs": 0
        },
        "fit": "Linear",
        "fn": 25,
        "include_baseline_error": false,
        "n": 25,
        "reviewed": true,
        "value": 0.00048367985254109186
    },
    "Ar40": {
        "error": 6.346419175592948e-05,
        "error_type": "SEM",
        "filter_outliers_dict": {
            "filter_outliers": false,
            "iterations": 0,
            "std_devs": 0
        },
        "fit": "Linear",
        "fn": 25,
        "include_baseline_error": false,
        "n": 25,
        "reviewed": true,
        "value": 0.22748516367629637
    }
}